src/FIFO.v
`timescale 1ns/1ps

module fifo #(
    parameter DATA_WIDTH = 8,
    parameter ADDR_WIDTH = 4
)(
    input wire clk,
    input wire rst,
    input wire wr_en,
    input wire rd_en,
    input wire [DATA_WIDTH-1:0] data_in,
    output reg [DATA_WIDTH-1:0] data_out,
    output reg full,
    output reg empty
);

    reg [DATA_WIDTH-1:0] mem [0:(1<<ADDR_WIDTH)-1];
    reg [ADDR_WIDTH-1:0] wr_ptr;
    reg [ADDR_WIDTH-1:0] rd_ptr;
    reg [ADDR_WIDTH:0] count;

    always @(posedge clk or posedge rst) begin
        if (rst) begin
            wr_ptr <= 0;
            rd_ptr <= 0;
            count <= 0;
            full <= 0;
            empty <= 1;
            data_out <= 0;
        end else begin
            if (wr_en && !full) begin
                mem[wr_ptr] <= data_in;
                wr_ptr <= wr_ptr + 1;
                count <= count + 1;
            end

            if (rd_en && !empty) begin
                data_out <= mem[rd_ptr];
                rd_ptr <= rd_ptr + 1;
                count <= count - 1;
            end

            if (count == (1<<ADDR_WIDTH)) begin
                full <= 1;
            end else begin
                full <= 0;
            end

            if (count == 0) begin
                empty <= 1;
            end else begin
                empty <= 0;
            end
        end
    end
endmodule

unit_tests/FIFO_tb_2.v
`timescale 1ns/1ps

module FIFO_tb;

    parameter DATA_WIDTH = 8;
    parameter ADDR_WIDTH = 4;

    reg clk;
    reg rst;
    reg wr_en;
    reg rd_en;
    reg [DATA_WIDTH-1:0] data_in;
    wire [DATA_WIDTH-1:0] data_out;
    wire full;
    wire empty;

    // Instantiate the FIFO module
    fifo #(
        .DATA_WIDTH(DATA_WIDTH),
        .ADDR_WIDTH(ADDR_WIDTH)
    ) uut (
        .clk(clk),
        .rst(rst),
        .wr_en(wr_en),
        .rd_en(rd_en),
        .data_in(data_in),
        .data_out(data_out),
        .full(full),
        .empty(empty)
    );

    // Clock Generation
    initial begin
        clk = 0;
        forever #5 clk = ~clk;
    end

    // Test sequence
    initial begin
        // Reset FIFO and prepare to write
        rst = 1;
        wr_en = 0;
        rd_en = 0;
        data_in = 0;
        #10;
        rst = 0;

        // Write 16 values to FIFO
        for (integer i = 1; i <= 16; i = i + 1) begin
            write_fifo(i);
        end

        // Attempt to write 17th value
        write_fifo(8'hFF);

        // Read all 16 values back from FIFO
        for (integer i = 1; i <= 16; i = i + 1) begin
            read_fifo();
        end

        // Reset the FIFO
        rst = 1;
        #10;
        rst = 0;

        // Finish simulation
        #20;
        $finish;
    end

    // Tasks for writing to and reading from the FIFO
    task write_fifo(input [DATA_WIDTH-1:0] data);
    begin
        wr_en = 1;
        data_in = data;
        #10;
        wr_en = 0;
        #10;
    end
    endtask

    task read_fifo();
    begin
        rd_en = 1;
        #10;
        rd_en = 0;
        #10;
    end
    endtask

    // Monitor outputs
    initial begin
        $monitor("Time: %0d, rst: %b, wr_en: %b, rd_en: %b, data_in: %h, data_out: %h, full: %b, empty: %b", 
                 $time, rst, wr_en, rd_en, data_in, data_out, full, empty);
    end 

    // VCD Dump
    initial begin
        $dumpfile("../test_output/FIFO_tb_2/FIFO_tb_2.vcd");
        $dumpvars(0, FIFO_tb);
    end

endmodule

test_output/FIFO_tb_2/FIFO_tb_2.vcd
$date
	Sat Aug  3 17:47:03 2024
$end
$version
	Icarus Verilog
$end
$timescale
	1ps
$end
$scope module FIFO_tb $end
$var wire 1 ! full $end
$var wire 1 " empty $end
$var wire 8 # data_out [7:0] $end
$var parameter 32 $ ADDR_WIDTH $end
$var parameter 32 % DATA_WIDTH $end
$var reg 1 & clk $end
$var reg 8 ' data_in [7:0] $end
$var reg 1 ( rd_en $end
$var reg 1 ) rst $end
$var reg 1 * wr_en $end
$scope module uut $end
$var wire 1 & clk $end
$var wire 8 + data_in [7:0] $end
$var wire 1 ( rd_en $end
$var wire 1 ) rst $end
$var wire 1 * wr_en $end
$var parameter 32 , ADDR_WIDTH $end
$var parameter 32 - DATA_WIDTH $end
$var reg 5 . count [4:0] $end
$var reg 8 / data_out [7:0] $end
$var reg 1 " empty $end
$var reg 1 ! full $end
$var reg 4 0 rd_ptr [3:0] $end
$var reg 4 1 wr_ptr [3:0] $end
$upscope $end
$scope begin $ivl_for_loop0 $end
$var integer 32 2 i [31:0] $end
$upscope $end
$scope begin $ivl_for_loop1 $end
$var integer 32 3 i [31:0] $end
$upscope $end
$scope task read_fifo $end
$upscope $end
$scope task write_fifo $end
$var reg 8 4 data [7:0] $end
$upscope $end
$upscope $end
$enddefinitions $end
$comment Show the parameter values. $end
$dumpall
b1000 -
b100 ,
b1000 %
b100 $
$end
#0
$dumpvars
bx 4
bx 3
bx 2
b0 1
b0 0
b0 /
b0 .
b0 +
0*
1)
0(
b0 '
0&
b0 #
1"
0!
$end
#5000
1&
#10000
0&
b1 '
b1 +
1*
b1 4
b1 2
0)
#15000
b1 .
b1 1
1&
#20000
0&
0*
#25000
0"
1&
#30000
0&
b10 '
b10 +
1*
b10 4
b10 2
#35000
b10 .
b10 1
1&
#40000
0&
0*
#45000
1&
#50000
0&
b11 '
b11 +
1*
b11 4
b11 2
#55000
b11 .
b11 1
1&
#60000
0&
0*
#65000
1&
#70000
0&
b100 '
b100 +
1*
b100 4
b100 2
#75000
b100 .
b100 1
1&
#80000
0&
0*
#85000
1&
#90000
0&
b101 '
b101 +
1*
b101 4
b101 2
#95000
b101 .
b101 1
1&
#100000
0&
0*
#105000
1&
#110000
0&
b110 '
b110 +
1*
b110 4
b110 2
#115000
b110 .
b110 1
1&
#120000
0&
0*
#125000
1&
#130000
0&
b111 '
b111 +
1*
b111 4
b111 2
#135000
b111 .
b111 1
1&
#140000
0&
0*
#145000
1&
#150000
0&
b1000 '
b1000 +
1*
b1000 4
b1000 2
#155000
b1000 .
b1000 1
1&
#160000
0&
0*
#165000
1&
#170000
0&
b1001 '
b1001 +
1*
b1001 4
b1001 2
#175000
b1001 .
b1001 1
1&
#180000
0&
0*
#185000
1&
#190000
0&
b1010 '
b1010 +
1*
b1010 4
b1010 2
#195000
b1010 .
b1010 1
1&
#200000
0&
0*
#205000
1&
#210000
0&
b1011 '
b1011 +
1*
b1011 4
b1011 2
#215000
b1011 .
b1011 1
1&
#220000
0&
0*
#225000
1&
#230000
0&
b1100 '
b1100 +
1*
b1100 4
b1100 2
#235000
b1100 .
b1100 1
1&
#240000
0&
0*
#245000
1&
#250000
0&
b1101 '
b1101 +
1*
b1101 4
b1101 2
#255000
b1101 .
b1101 1
1&
#260000
0&
0*
#265000
1&
#270000
0&
b1110 '
b1110 +
1*
b1110 4
b1110 2
#275000
b1110 .
b1110 1
1&
#280000
0&
0*
#285000
1&
#290000
0&
b1111 '
b1111 +
1*
b1111 4
b1111 2
#295000
b1111 .
b1111 1
1&
#300000
0&
0*
#305000
1&
#310000
0&
b10000 '
b10000 +
1*
b10000 4
b10000 2
#315000
b10000 .
b0 1
1&
#320000
0&
0*
#325000
1!
1&
#330000
0&
b11111111 '
b11111111 +
1*
b11111111 4
b10001 2
#335000
1&
#340000
0&
0*
#345000
1&
#350000
0&
1(
b1 3
#355000
b1111 .
b1 0
b1 #
b1 /
1&
#360000
0&
0(
#365000
0!
1&
#370000
0&
1(
b10 3
#375000
b1110 .
b10 0
b10 #
b10 /
1&
#380000
0&
0(
#385000
1&
#390000
0&
1(
b11 3
#395000
b1101 .
b11 0
b11 #
b11 /
1&
#400000
0&
0(
#405000
1&
#410000
0&
1(
b100 3
#415000
b1100 .
b100 0
b100 #
b100 /
1&
#420000
0&
0(
#425000
1&
#430000
0&
1(
b101 3
#435000
b1011 .
b101 0
b101 #
b101 /
1&
#440000
0&
0(
#445000
1&
#450000
0&
1(
b110 3
#455000
b1010 .
b110 0
b110 #
b110 /
1&
#460000
0&
0(
#465000
1&
#470000
0&
1(
b111 3
#475000
b1001 .
b111 0
b111 #
b111 /
1&
#480000
0&
0(
#485000
1&
#490000
0&
1(
b1000 3
#495000
b1000 .
b1000 0
b1000 #
b1000 /
1&
#500000
0&
0(
#505000
1&
#510000
0&
1(
b1001 3
#515000
b111 .
b1001 0
b1001 #
b1001 /
1&
#520000
0&
0(
#525000
1&
#530000
0&
1(
b1010 3
#535000
b110 .
b1010 0
b1010 #
b1010 /
1&
#540000
0&
0(
#545000
1&
#550000
0&
1(
b1011 3
#555000
b101 .
b1011 0
b1011 #
b1011 /
1&
#560000
0&
0(
#565000
1&
#570000
0&
1(
b1100 3
#575000
b100 .
b1100 0
b1100 #
b1100 /
1&
#580000
0&
0(
#585000
1&
#590000
0&
1(
b1101 3
#595000
b11 .
b1101 0
b1101 #
b1101 /
1&
#600000
0&
0(
#605000
1&
#610000
0&
1(
b1110 3
#615000
b10 .
b1110 0
b1110 #
b1110 /
1&
#620000
0&
0(
#625000
1&
#630000
0&
1(
b1111 3
#635000
b1 .
b1111 0
b1111 #
b1111 /
1&
#640000
0&
0(
#645000
1&
#650000
0&
1(
b10000 3
#655000
b0 .
b0 0
b10000 #
b10000 /
1&
#660000
0&
0(
#665000
1"
1&
#670000
b0 #
b0 /
0&
1)
b10001 3
#675000
1&
#680000
0&
0)
