src/FIFO.v
`timescale 1ns/1ps

module fifo #(
    parameter DATA_WIDTH = 8,
    parameter ADDR_WIDTH = 4
)(
    input wire clk,
    input wire rst,
    input wire wr_en,
    input wire rd_en,
    input wire [DATA_WIDTH-1:0] data_in,
    output reg [DATA_WIDTH-1:0] data_out,
    output reg full,
    output reg empty
);

    reg [DATA_WIDTH-1:0] mem [0:(1<<ADDR_WIDTH)-1];
    reg [ADDR_WIDTH-1:0] wr_ptr;
    reg [ADDR_WIDTH-1:0] rd_ptr;
    reg [ADDR_WIDTH:0] count;

    always @(posedge clk or posedge rst) begin
        if (rst) begin
            wr_ptr <= 0;
            rd_ptr <= 0;
            count <= 0;
            full <= 0;
            empty <= 1;
            data_out <= 0;
        end else begin
            if (wr_en && !full) begin
                mem[wr_ptr] <= data_in;
                wr_ptr <= wr_ptr + 1;
                count <= count + 1;
            end

            if (rd_en && !empty) begin
                data_out <= mem[rd_ptr];
                rd_ptr <= rd_ptr + 1;
                count <= count - 1;
            end

            if (count == (1<<ADDR_WIDTH)) begin
                full <= 1;
            end else begin
                full <= 0;
            end

            if (count == 0) begin
                empty <= 1;
            end else begin
                empty <= 0;
            end
        end
    end
endmodule

unit_tests/FIFO_tb_1.v
`timescale 1ns/1ps

module FIFO_tb;

    parameter DATA_WIDTH = 8;
    parameter ADDR_WIDTH = 4;

    reg clk;
    reg rst;
    reg wr_en;
    reg rd_en;
    reg [DATA_WIDTH-1:0] data_in;
    wire [DATA_WIDTH-1:0] data_out;
    wire full;
    wire empty;

    // Instantiate the FIFO module
    fifo #(
        .DATA_WIDTH(DATA_WIDTH),
        .ADDR_WIDTH(ADDR_WIDTH)
    ) uut (
        .clk(clk),
        .rst(rst),
        .wr_en(wr_en),
        .rd_en(rd_en),
        .data_in(data_in),
        .data_out(data_out),
        .full(full),
        .empty(empty)
    );

    // Clock Generation
    initial begin
        clk = 0;
        forever #5 clk = ~clk;
    end

    // Test sequence
    initial begin
        // Reset FIFO and prepare to write
        rst = 1;
        wr_en = 0;
        rd_en = 0;
        data_in = 0;
        #10;
        rst = 0;

        // Write multiple values to FIFO
        write_fifo(8'hA1);
        write_fifo(8'hB2);
        write_fifo(8'hC3);

        // Read values back from FIFO
        read_fifo();
        read_fifo();
        read_fifo();

        // Finish simulation
        #20;
        $finish;
    end

    // Tasks for writing to and reading from the FIFO
    task write_fifo(input [DATA_WIDTH-1:0] data);
    begin
        wr_en = 1;
        data_in = data;
        #10;
        wr_en = 0;
        #10;
    end
    endtask

    task read_fifo();
    begin
        rd_en = 1;
        #10;
        rd_en = 0;
        #10;
    end
    endtask

    // Monitor outputs
    initial begin
        $monitor("Time: %0d, rst: %b, wr_en: %b, rd_en: %b, data_in: %h, data_out: %h, full: %b, empty: %b", 
                 $time, rst, wr_en, rd_en, data_in, data_out, full, empty);
    end 

    // VCD Dump
    initial begin
        $dumpfile("../test_output/FIFO_tb_1/FIFO_tb_1.vcd");
        $dumpvars(0, FIFO_tb);
    end

endmodule

test_output/FIFO_tb_0/FIFO_tb_0.vcd
$date
	Sat Aug  3 14:52:48 2024
$end
$version
	Icarus Verilog
$end
$timescale
	1ps
$end
$scope module FIFO_tb $end
$var wire 1 ! full $end
$var wire 1 " empty $end
$var wire 8 # data_out [7:0] $end
$var parameter 32 $ ADDR_WIDTH $end
$var parameter 32 % DATA_WIDTH $end
$var reg 1 & clk $end
$var reg 8 ' data_in [7:0] $end
$var reg 1 ( rd_en $end
$var reg 1 ) rst $end
$var reg 1 * wr_en $end
$scope module uut $end
$var wire 1 & clk $end
$var wire 8 + data_in [7:0] $end
$var wire 1 ( rd_en $end
$var wire 1 ) rst $end
$var wire 1 * wr_en $end
$var wire 1 ! full $end
$var wire 1 " empty $end
$var parameter 32 , ADDR_WIDTH $end
$var parameter 32 - DATA_WIDTH $end
$var reg 4 . count [3:0] $end
$var reg 8 / data_out [7:0] $end
$var reg 4 0 rd_ptr [3:0] $end
$var reg 4 1 wr_ptr [3:0] $end
$upscope $end
$upscope $end
$enddefinitions $end
$comment Show the parameter values. $end
$dumpall
b1000 -
b100 ,
b1000 %
b100 $
$end
#0
$dumpvars
b0 1
b0 0
b0 /
b0 .
b0 +
0*
1)
0(
b0 '
0&
b0 #
1"
0!
$end
#5000
1&
#10000
0&
0)
#15000
1&
#20000
0&
b10100101 '
b10100101 +
1*
#25000
0"
b1 .
b1 1
1&
#30000
0&
0*
#35000
1&
#40000
0&
1(
#45000
1"
b0 .
b1 0
b10100101 #
b10100101 /
1&
#50000
0&
0(
